kilroy_face_client_py_sdk/__init__.py
kilroy_face_client_py_sdk/client.py
kilroy_face_client_py_sdk/resources/__init__.py
kilroy_face_client_py_sdk-0.8.0.dist-info/LICENSE
kilroy_face_client_py_sdk-0.8.0.dist-info/WHEEL
kilroy_face_client_py_sdk-0.8.0.dist-info/METADATA
kilroy_face_client_py_sdk-0.8.0.dist-info/RECORD
