Metadata-Version: 2.1
Name: kilroy-face-client-py-sdk
Version: 0.8.0
Summary: SDK for kilroy face clients in Python 🧰
Home-page: https://github.com/kilroybot/kilroy-face-client-py-sdk
Author: kilroy
Author-email: kilroymail@pm.me
Requires-Python: >=3.10,<4.0
Classifier: License :: OSI Approved :: MIT License
Classifier: Operating System :: OS Independent
Classifier: Programming Language :: Python :: 3
Classifier: Programming Language :: Python :: 3.10
Requires-Dist: kilroy-face-py-shared (>=0.6,<0.7)
Project-URL: Documentation, https://kilroybot.github.io/kilroy-face-client-py-sdk
Project-URL: Repository, https://github.com/kilroybot/kilroy-face-client-py-sdk
